bigeye_aws/__init__.py
bigeye_aws/__version__.py
bigeye_aws/functions/__init__.py
bigeye_aws/functions/athena.py
bigeye_aws/functions/aws.py
bigeye_aws/functions/s3.py
bigeye_aws-0.0.9.dist-info/METADATA
bigeye_aws-0.0.9.dist-info/WHEEL
bigeye_aws-0.0.9.dist-info/entry_points.txt
bigeye_aws-0.0.9.dist-info/top_level.txt
bigeye_aws-0.0.9.dist-info/RECORD
