Metadata-Version: 2.1
Name: bigeye-aws
Version: 0.0.9
Summary: Bigeye AWS Library.
Home-page: UNKNOWN
Author: Bigeye
Author-email: support@bigeye.com
License: Apache License Version 2.0
Platform: UNKNOWN
Classifier: Programming Language :: Python :: 3.7
Classifier: Operating System :: OS Independent
Requires-Python: >=3.7
Requires-Dist: boto3 (~=1.19.9)
Requires-Dist: bigeye-sdk (<0.5.0,>=0.4.0)
